opentelemetry/instrumentation/openai_agents/__init__.py
opentelemetry/instrumentation/openai_agents/package.py
opentelemetry/instrumentation/openai_agents/span_processor.py
opentelemetry/instrumentation/openai_agents/version.py
splunk_otel_instrumentation_openai_agents-0.1.2.dist-info/METADATA
splunk_otel_instrumentation_openai_agents-0.1.2.dist-info/WHEEL
splunk_otel_instrumentation_openai_agents-0.1.2.dist-info/entry_points.txt
splunk_otel_instrumentation_openai_agents-0.1.2.dist-info/licenses/LICENSE
splunk_otel_instrumentation_openai_agents-0.1.2.dist-info/RECORD
