Metadata-Version: 2.4
Name: splunk-otel-instrumentation-openai-agents
Version: 0.1.2
Summary: Splunk OpenTelemetry OpenAI Agents instrumentation
Project-URL: Homepage, https://github.com/open-telemetry/opentelemetry-python-contrib/tree/main/instrumentation-genai/opentelemetry-instrumentation-openai-agents-v2
Project-URL: Repository, https://github.com/open-telemetry/opentelemetry-python-contrib
License-Expression: Apache-2.0
License-File: LICENSE
Classifier: Development Status :: 4 - Beta
Classifier: Intended Audience :: Developers
Classifier: License :: OSI Approved :: Apache Software License
Classifier: Programming Language :: Python
Classifier: Programming Language :: Python :: 3
Classifier: Programming Language :: Python :: 3.9
Classifier: Programming Language :: Python :: 3.10
Classifier: Programming Language :: Python :: 3.11
Classifier: Programming Language :: Python :: 3.12
Classifier: Programming Language :: Python :: 3.13
Requires-Python: >=3.9
Requires-Dist: opentelemetry-api>=1.37
Requires-Dist: opentelemetry-instrumentation>=0.58b0
Requires-Dist: opentelemetry-semantic-conventions>=0.58b0
Requires-Dist: splunk-otel-util-genai>=0.1.9
Provides-Extra: instruments
Requires-Dist: openai-agents>=0.3.3; extra == 'instruments'
